MANIFEST.in
README.md
requirements.txt
setup.cfg
setup.py
versioneer.py
botcity/plugins/hashicorp/vault/__init__.py
botcity/plugins/hashicorp/vault/_version.py
botcity/plugins/hashicorp/vault/kv/__init__.py
botcity/plugins/hashicorp/vault/kv/plugin.py
botcity_hashicorp_vault_plugin.egg-info/PKG-INFO
botcity_hashicorp_vault_plugin.egg-info/SOURCES.txt
botcity_hashicorp_vault_plugin.egg-info/dependency_links.txt
botcity_hashicorp_vault_plugin.egg-info/requires.txt
botcity_hashicorp_vault_plugin.egg-info/top_level.txt