Metadata-Version: 2.1
Name: botcity-hashicorp-vault-plugin
Version: 0.1.2
Home-page: https://bitbucket.org/botcitydev/bot-hashicorp-vault-plugin-python.git
Requires-Python: >=3.7
